bixypay/__init__.py
bixypay/client.py
bixypay/types.py
bixypay_sdk-1.0.0.dist-info/METADATA
bixypay_sdk-1.0.0.dist-info/WHEEL
bixypay_sdk-1.0.0.dist-info/top_level.txt
bixypay_sdk-1.0.0.dist-info/RECORD
