Metadata-Version: 2.4
Name: bixypay-sdk
Version: 1.0.0
Summary: Official Python SDK for the BixyPay Fintech API Platform
Home-page: https://github.com/bixypay/fintech-sdk-python
Author: BixyPay
Author-email: developers@bixypay.com
Project-URL: Bug Reports, https://github.com/bixypay/fintech-sdk-python/issues
Project-URL: Documentation, https://docs.bixypay.com
Project-URL: Source, https://github.com/bixypay/fintech-sdk-python
Keywords: bixypay fintech payment crypto api sdk
Classifier: Development Status :: 5 - Production/Stable
Classifier: Intended Audience :: Developers
Classifier: License :: OSI Approved :: MIT License
Classifier: Operating System :: OS Independent
Classifier: Programming Language :: Python :: 3
Classifier: Programming Language :: Python :: 3.7
Classifier: Programming Language :: Python :: 3.8
Classifier: Programming Language :: Python :: 3.9
Classifier: Programming Language :: Python :: 3.10
Classifier: Programming Language :: Python :: 3.11
Classifier: Topic :: Software Development :: Libraries :: Python Modules
Classifier: Topic :: Office/Business :: Financial
Requires-Python: >=3.7
Requires-Dist: requests>=2.28.0
Dynamic: author
Dynamic: author-email
Dynamic: classifier
Dynamic: description
Dynamic: description-content-type
Dynamic: home-page
Dynamic: keywords
Dynamic: project-url
Dynamic: requires-dist
Dynamic: requires-python
Dynamic: summary
